{
  "company_name": "GREAT BRITISH BREWORKS LTD",
  "company_number": "10443894",
  "company_status": "liquidation",
  "company_type": "ltd",
  "kind": "search-results#company",
  "links": {
    "company_profile": "/company/10443894"
  },
  "date_of_creation": "2016-10-25",
  "registered_office_address": {
    "address_line_1": "Leonard Curtis House",
    "address_line_2": "Elms Square, Bury New Road",
    "locality": "Whitefield",
    "postal_code": "M45 7TA",
    "region": "Greater Manchester"
  },
  "sic_codes": [
    "11050"
  ],
  "filling_history": [
    {
      "transaction_id": "MzQzMTk3MjQ1MWFkaXF6a2N4",
      "barcode": "YD9E9LM0",
      "type": "AD01",
      "date": "2024-08-19",
      "category": "address",
      "description": "change-registered-office-address-company-with-date-old-address-new-address",
      "description_values": {
        "change_date": "2024-08-19",
        "old_address": "The Black Swan Birdgate Pickering YO18 7AL United Kingdom",
        "new_address": "Leonard Curtis House Elms Square, Bury New Road Whitefield Greater Manchester M45 7TA"
      },
      "pages": 3,
      "action_date": "2024-08-19",
      "paper_filed": true,
      "links": {
        "self": "/company/10443894/filing-history/MzQzMTk3MjQ1MWFkaXF6a2N4",
        "document_metadata": "https://document-api.company-information.service.gov.uk/document/h2nbnATbDyubh6lfFHDjX73XFzql-YITJSRM94lQorE"
      }
    },
    {
      "transaction_id": "MzQzMTk3MjczNmFkaXF6a2N4",
      "barcode": "YD9E9MSQ",
      "type": "LIQ02",
      "date": "2024-08-19",
      "category": "insolvency",
      "subcategory": "voluntary",
      "description": "liquidation-voluntary-statement-of-affairs",
      "pages": 11,
      "paper_filed": true,
      "links": {
        "self": "/company/10443894/filing-history/MzQzMTk3MjczNmFkaXF6a2N4",
        "document_metadata": "https://document-api.company-information.service.gov.uk/document/PehvPzw4W4nBtCD7vkCsZWoWBRbqgNknPc0--x_3Q-M"
      }
    },
    {
      "transaction_id": "MzQzMTk3Mjg5OWFkaXF6a2N4",
      "barcode": "YD9E9NCR",
      "type": "600",
      "date": "2024-08-19",
      "category": "insolvency",
      "subcategory": "voluntary",
      "description": "liquidation-voluntary-appointment-of-liquidator",
      "pages": 4,
      "paper_filed": true,
      "links": {
        "self": "/company/10443894/filing-history/MzQzMTk3Mjg5OWFkaXF6a2N4",
        "document_metadata": "https://document-api.company-information.service.gov.uk/document/wrDH1hEvog4fTcykr3DmXcsdoH6xGuPpmZ5tAQVPbmg"
      }
    },
    {
      "transaction_id": "WUQ5RTlNU0lhZGlxemtjeA",
      "barcode": "YD9E9MSI",
      "type": "RESOLUTIONS",
      "date": "2024-08-19",
      "category": "resolution",
      "resolutions": [
        {
          "category": "liquidation",
          "description": "liquidation-voluntary-extraordinary-resolution-to-wind-up-with-case-start-date",
          "type": "LRESEX",
          "subcategory": [
            "voluntary",
            "resolution"
          ],
          "description_values": {
            "case_start_date": "2024-08-12"
          },
          "original_description": "Extraordinary resolution to wind up"
        }
      ],
      "description": "resolution",
      "description_values": {
        "description": "Resolutions"
      },
      "pages": 1,
      "paper_filed": true,
      "links": {
        "self": "/company/10443894/filing-history/WUQ5RTlNU0lhZGlxemtjeA",
        "document_metadata": "https://document-api.company-information.service.gov.uk/document/hdwqb1v3rlkFg5HbsAOzKX5BPFEguqRR1ol-DcHcNmI"
      }
    },
    {
      "transaction_id": "MzQxMTYwNzI2MmFkaXF6a2N4",
      "barcode": "XCX63JWR",
      "type": "PSC04",
      "date": "2024-02-19",
      "category": "persons-with-significant-control",
      "subcategory": "change",
      "description": "change-to-a-person-with-significant-control",
      "description_values": {
        "change_date": "2024-02-19",
        "psc_name": "Mr Tristan Philip Hall"
      },
      "pages": 2,
      "action_date": "2024-02-19",
      "links": {
        "self": "/company/10443894/filing-history/MzQxMTYwNzI2MmFkaXF6a2N4",
        "document_metadata": "https://document-api.company-information.service.gov.uk/document/GpiCljZGByTeHbLAR5mVsj2T4VEMzQaFt09rDUd_rU8"
      }
    },
    {
      "transaction_id": "MzQxMTYwNzA0M2FkaXF6a2N4",
      "barcode": "XCX63J88",
      "type": "TM01",
      "date": "2024-02-19",
      "category": "officers",
      "subcategory": "termination",
      "description": "termination-director-company-with-name-termination-date",
      "description_values": {
        "officer_name": "Mehmet Borga Es",
        "termination_date": "2024-02-19"
      },
      "pages": 1,
      "action_date": "2024-02-19",
      "links": {
        "self": "/company/10443894/filing-history/MzQxMTYwNzA0M2FkaXF6a2N4",
        "document_metadata": "https://document-api.company-information.service.gov.uk/document/LNLDrOKQuEccaYKPe-PvdcPvDXqAYGm5FYQkHYs73pw"
      }
    },
    {
      "transaction_id": "MzQxMDc2Njk4MmFkaXF6a2N4",
      "barcode": "XCWPTDE0",
      "type": "CS01",
      "date": "2024-02-12",
      "category": "confirmation-statement",
      "description": "confirmation-statement-with-no-updates",
      "description_values": {
        "made_up_date": "2024-02-10"
      },
      "pages": 3,
      "action_date": "2024-02-10",
      "links": {
        "self": "/company/10443894/filing-history/MzQxMDc2Njk4MmFkaXF6a2N4",
        "document_metadata": "https://document-api.company-information.service.gov.uk/document/JH3U_sctobXo0fXhPvEXG6K46e6W6mIiHF5HEdSRRyQ"
      }
    },
    {
      "transaction_id": "MzQxMDc1MzI2NmFkaXF6a2N4",
      "barcode": "XCWPSBG3",
      "type": "CH01",
      "date": "2024-02-12",
      "category": "officers",
      "subcategory": "change",
      "description": "change-person-director-company-with-change-date",
      "description_values": {
        "change_date": "2024-02-12",
        "officer_name": "Mr Mehmet Borga Es"
      },
      "pages": 2,
      "action_date": "2024-02-12",
      "links": {
        "self": "/company/10443894/filing-history/MzQxMDc1MzI2NmFkaXF6a2N4",
        "document_metadata": "https://document-api.company-information.service.gov.uk/document/_V5uaW8EcyqYyCbAz6ujjU9js_SOhJZy9UKwwqX5_WI"
      }
    },
    {
      "transaction_id": "MzM5ODQ1NTU1NGFkaXF6a2N4",
      "barcode": "XCFBVFUZ",
      "type": "AA",
      "date": "2023-10-31",
      "category": "accounts",
      "description": "accounts-with-accounts-type-total-exemption-full",
      "description_values": {
        "made_up_date": "2023-01-31"
      },
      "pages": 8,
      "action_date": "2023-01-31",
      "links": {
        "self": "/company/10443894/filing-history/MzM5ODQ1NTU1NGFkaXF6a2N4",
        "document_metadata": "https://document-api.company-information.service.gov.uk/document/wU8VRylymZKVEK9u87mvBL2fZ4GXy7syy1xroXl-rPQ"
      }
    },
    {
      "transaction_id": "MzM2OTAxMTE3M2FkaXF6a2N4",
      "barcode": "XBX8V876",
      "type": "CS01",
      "date": "2023-02-13",
      "category": "confirmation-statement",
      "description": "confirmation-statement-with-no-updates",
      "description_values": {
        "made_up_date": "2023-02-10"
      },
      "pages": 3,
      "action_date": "2023-02-10",
      "links": {
        "self": "/company/10443894/filing-history/MzM2OTAxMTE3M2FkaXF6a2N4",
        "document_metadata": "https://document-api.company-information.service.gov.uk/document/8lwV7PwKj8dnMRZNtb18j7qKNY_jpwDf-ru8qgxxgYE"
      }
    },
    {
      "transaction_id": "MzM1Njg0OTQ3OWFkaXF6a2N4",
      "barcode": "XBFLAOA3",
      "type": "AA",
      "date": "2022-10-28",
      "category": "accounts",
      "description": "accounts-with-accounts-type-total-exemption-full",
      "description_values": {
        "made_up_date": "2022-01-31"
      },
      "pages": 8,
      "action_date": "2022-01-31",
      "links": {
        "self": "/company/10443894/filing-history/MzM1Njg0OTQ3OWFkaXF6a2N4",
        "document_metadata": "https://document-api.company-information.service.gov.uk/document/aQOIAR7PKjmaxVqL7O4KD-tZGs18z9ekgrnNOvpqdqc"
      }
    },
    {
      "transaction_id": "MzMyOTczMzcwNWFkaXF6a2N4",
      "barcode": "XAXUCAP6",
      "type": "CS01",
      "date": "2022-02-14",
      "category": "confirmation-statement",
      "description": "confirmation-statement-with-no-updates",
      "description_values": {
        "made_up_date": "2022-02-10"
      },
      "pages": 3,
      "action_date": "2022-02-10",
      "links": {
        "self": "/company/10443894/filing-history/MzMyOTczMzcwNWFkaXF6a2N4",
        "document_metadata": "https://document-api.company-information.service.gov.uk/document/E3vMjqr4z65a6enb2gabMh0Nq9C1mOi3WMjZzsa75CQ"
      }
    },
    {
      "transaction_id": "MzMxODE2NTE3MWFkaXF6a2N4",
      "barcode": "XAFWOGDS",
      "type": "AA",
      "date": "2021-10-26",
      "category": "accounts",
      "description": "accounts-with-accounts-type-total-exemption-full",
      "description_values": {
        "made_up_date": "2021-01-31"
      },
      "pages": 8,
      "action_date": "2021-01-31",
      "links": {
        "self": "/company/10443894/filing-history/MzMxODE2NTE3MWFkaXF6a2N4",
        "document_metadata": "https://document-api.company-information.service.gov.uk/document/Tk5rZE_4kFIqVsYYUM5jefOdkkIxiMtMCVRzLyE7sNY"
      }
    },
    {
      "transaction_id": "MzMwNzU0NTYzNGFkaXF6a2N4",
      "barcode": "XA8K60O1",
      "type": "AA01",
      "date": "2021-07-13",
      "category": "accounts",
      "description": "change-account-reference-date-company-previous-extended",
      "description_values": {
        "made_up_date": "2020-10-31",
        "new_date": "2021-01-31"
      },
      "pages": 1,
      "action_date": "2021-01-31",
      "links": {
        "self": "/company/10443894/filing-history/MzMwNzU0NTYzNGFkaXF6a2N4",
        "document_metadata": "https://document-api.company-information.service.gov.uk/document/ASXPrtTZl8718dkieyUPkzZHH33h2t8gCQTMkXGQxRg"
      }
    },
    {
      "transaction_id": "MzI5MTEwNTMwNWFkaXF6a2N4",
      "barcode": "X9Y0K77D",
      "type": "CS01",
      "date": "2021-02-10",
      "category": "confirmation-statement",
      "description": "confirmation-statement-with-updates",
      "description_values": {
        "made_up_date": "2021-02-10"
      },
      "pages": 4,
      "action_date": "2021-02-10",
      "links": {
        "self": "/company/10443894/filing-history/MzI5MTEwNTMwNWFkaXF6a2N4",
        "document_metadata": "https://document-api.company-information.service.gov.uk/document/a-2jHJzbeRo0L0Ex4YnbVOiU39xyJhPVCXj5Apd3ZnE"
      }
    },
    {
      "transaction_id": "MzI5MTEwMTgwNGFkaXF6a2N4",
      "barcode": "X9Y0JQSA",
      "type": "PSC02",
      "date": "2021-02-10",
      "category": "persons-with-significant-control",
      "subcategory": "notifications",
      "description": "notification-of-a-person-with-significant-control",
      "description_values": {
        "psc_name": "Breworks Ltd",
        "notification_date": "2021-02-08"
      },
      "pages": 2,
      "action_date": "2021-02-08",
      "links": {
        "self": "/company/10443894/filing-history/MzI5MTEwMTgwNGFkaXF6a2N4",
        "document_metadata": "https://document-api.company-information.service.gov.uk/document/7wk1ED9tIu6VlEwvFUCOd95OTNRiyI3hX9kVnIobAfw"
      }
    },
    {
      "transaction_id": "MzI5MTEwMTU3OWFkaXF6a2N4",
      "barcode": "X9Y0JQBK",
      "type": "PSC07",
      "date": "2021-02-10",
      "category": "persons-with-significant-control",
      "subcategory": "termination",
      "description": "cessation-of-a-person-with-significant-control",
      "description_values": {
        "psc_name": "Mehmet Borga Es",
        "cessation_date": "2021-02-08"
      },
      "pages": 1,
      "action_date": "2021-02-08",
      "links": {
        "self": "/company/10443894/filing-history/MzI5MTEwMTU3OWFkaXF6a2N4",
        "document_metadata": "https://document-api.company-information.service.gov.uk/document/JCTGJPa5FpzbtVpg6TX468SAXf2sEROHi0Y37zxHMa0"
      }
    },
    {
      "transaction_id": "MzI5MTEwMTQ4M2FkaXF6a2N4",
      "barcode": "X9Y0JPOW",
      "type": "PSC07",
      "date": "2021-02-10",
      "category": "persons-with-significant-control",
      "subcategory": "termination",
      "description": "cessation-of-a-person-with-significant-control",
      "description_values": {
        "psc_name": "Philip Robert Hall",
        "cessation_date": "2021-02-08"
      },
      "pages": 1,
      "action_date": "2021-02-08",
      "links": {
        "self": "/company/10443894/filing-history/MzI5MTEwMTQ4M2FkaXF6a2N4",
        "document_metadata": "https://document-api.company-information.service.gov.uk/document/-kqjKbLoiUQCuI3bSqKXEkn2dGh2ZnpUaOyRE6FI9Z8"
      }
    },
    {
      "transaction_id": "MzI4NTczMTcxMGFkaXF6a2N4",
      "barcode": "X9JNYEFD",
      "type": "CS01",
      "date": "2020-12-11",
      "category": "confirmation-statement",
      "description": "confirmation-statement-with-no-updates",
      "description_values": {
        "made_up_date": "2020-10-24"
      },
      "pages": 3,
      "action_date": "2020-10-24",
      "links": {
        "self": "/company/10443894/filing-history/MzI4NTczMTcxMGFkaXF6a2N4",
        "document_metadata": "https://document-api.company-information.service.gov.uk/document/9m_zVk7JZe5vmNoPh8_E-i2D0q3oW9TRwjRKM28iw8c"
      }
    },
    {
      "transaction_id": "MzI4MTAzODQxMGFkaXF6a2N4",
      "barcode": "X9G3IJ01",
      "type": "AA",
      "date": "2020-10-20",
      "category": "accounts",
      "description": "accounts-with-accounts-type-total-exemption-full",
      "description_values": {
        "made_up_date": "2019-10-31"
      },
      "pages": 6,
      "action_date": "2019-10-31",
      "links": {
        "self": "/company/10443894/filing-history/MzI4MTAzODQxMGFkaXF6a2N4",
        "document_metadata": "https://document-api.company-information.service.gov.uk/document/m0Dt4Kl23vpKVXw9TozzE8uya-beyBMchbs7vs8dHJA"
      }
    },
    {
      "transaction_id": "MzI0ODMzNzgxOWFkaXF6a2N4",
      "barcode": "X8HB08O1",
      "type": "CS01",
      "date": "2019-11-01",
      "category": "confirmation-statement",
      "description": "confirmation-statement-with-updates",
      "description_values": {
        "made_up_date": "2019-10-24"
      },
      "pages": 4,
      "action_date": "2019-10-24",
      "links": {
        "self": "/company/10443894/filing-history/MzI0ODMzNzgxOWFkaXF6a2N4",
        "document_metadata": "https://document-api.company-information.service.gov.uk/document/WwcLTG0SkisyO-JlHFLG6acS0GGHjWkZOmE__zzPx9U"
      }
    },
    {
      "transaction_id": "MzI0NTE5MjA4MmFkaXF6a2N4",
      "barcode": "X8EPV39K",
      "type": "PSC01",
      "date": "2019-09-25",
      "category": "persons-with-significant-control",
      "subcategory": "notifications",
      "description": "notification-of-a-person-with-significant-control",
      "description_values": {
        "psc_name": "Philip Robert Hall",
        "notification_date": "2019-09-01"
      },
      "pages": 2,
      "action_date": "2019-09-01",
      "links": {
        "self": "/company/10443894/filing-history/MzI0NTE5MjA4MmFkaXF6a2N4",
        "document_metadata": "https://document-api.company-information.service.gov.uk/document/IdJ915dTggxVy15gDDqqwLWCw7aFIhv8ccTakDh5Fqk"
      }
    },
    {
      "transaction_id": "MzI0NTE5MTc1OWFkaXF6a2N4",
      "barcode": "X8EPV24A",
      "type": "PSC01",
      "date": "2019-09-25",
      "category": "persons-with-significant-control",
      "subcategory": "notifications",
      "description": "notification-of-a-person-with-significant-control",
      "description_values": {
        "psc_name": "Mehmet Borga Es",
        "notification_date": "2019-09-01"
      },
      "pages": 2,
      "action_date": "2019-09-01",
      "links": {
        "self": "/company/10443894/filing-history/MzI0NTE5MTc1OWFkaXF6a2N4",
        "document_metadata": "https://document-api.company-information.service.gov.uk/document/0WMByoNYdbYoOQvR3gYcDgNKyy34AILdCK4A05ivK38"
      }
    },
    {
      "transaction_id": "MzI0NTE4NTc4OWFkaXF6a2N4",
      "barcode": "X8EPUEQR",
      "type": "AP01",
      "date": "2019-09-25",
      "category": "officers",
      "subcategory": "appointments",
      "description": "appoint-person-director-company-with-name-date",
      "description_values": {
        "officer_name": "Mr Mehmet Borga Es",
        "appointment_date": "2019-09-01"
      },
      "pages": 2,
      "action_date": "2019-09-01",
      "links": {
        "self": "/company/10443894/filing-history/MzI0NTE4NTc4OWFkaXF6a2N4",
        "document_metadata": "https://document-api.company-information.service.gov.uk/document/T9tiHIUeNb5aiNGURifhUjCNIqp3MHcLbP6hHwe4Te4"
      }
    },
    {
      "transaction_id": "MzI0NTE4NTQxMGFkaXF6a2N4",
      "barcode": "X8EPUDIO",
      "type": "TM01",
      "date": "2019-09-25",
      "category": "officers",
      "subcategory": "termination",
      "description": "termination-director-company-with-name-termination-date",
      "description_values": {
        "officer_name": "Jill Hall",
        "termination_date": "2019-09-01"
      },
      "pages": 1,
      "action_date": "2019-09-01",
      "links": {
        "self": "/company/10443894/filing-history/MzI0NTE4NTQxMGFkaXF6a2N4",
        "document_metadata": "https://document-api.company-information.service.gov.uk/document/zqGc3X30JF_cY44ASdyey1rbrR1xxGxmpVGdJZM3tH0"
      }
    },
    {
      "transaction_id": "MzIzOTE0NjMzOWFkaXF6a2N4",
      "barcode": "X89I8ZWY",
      "type": "AA",
      "date": "2019-07-11",
      "category": "accounts",
      "description": "accounts-with-accounts-type-dormant",
      "description_values": {
        "made_up_date": "2018-10-31"
      },
      "pages": 7,
      "action_date": "2018-10-31",
      "links": {
        "self": "/company/10443894/filing-history/MzIzOTE0NjMzOWFkaXF6a2N4",
        "document_metadata": "https://document-api.company-information.service.gov.uk/document/GumodqzlivEAsPYFid2a3B8rjCZDfIn5BmSTxvLz_jc"
      }
    },
    {
      "transaction_id": "MzIyMTkwODE2MmFkaXF6a2N4",
      "barcode": "X7KNMDZT",
      "type": "CS01",
      "date": "2018-12-12",
      "category": "confirmation-statement",
      "description": "confirmation-statement-with-no-updates",
      "description_values": {
        "made_up_date": "2018-10-24"
      },
      "pages": 3,
      "action_date": "2018-10-24",
      "links": {
        "self": "/company/10443894/filing-history/MzIyMTkwODE2MmFkaXF6a2N4",
        "document_metadata": "https://document-api.company-information.service.gov.uk/document/zvGOTIT0aTa1Yc7vAPEkFi5ljwwiU4TxAmrdw-VWNXI"
      }
    },
    {
      "transaction_id": "MzIxMDIwMDMxOGFkaXF6a2N4",
      "barcode": "X7ALTKWA",
      "type": "AA",
      "date": "2018-07-20",
      "category": "accounts",
      "description": "accounts-with-accounts-type-unaudited-abridged",
      "description_values": {
        "made_up_date": "2017-10-31"
      },
      "pages": 6,
      "links": {
        "self": "/company/10443894/filing-history/MzIxMDIwMDMxOGFkaXF6a2N4",
        "document_metadata": "https://document-api.company-information.service.gov.uk/document/S7u7qlwtVM6lL2VGor0BmS-BzZ1Qzy5s7SxqQke1Vv4"
      }
    },
    {
      "transaction_id": "MzE5MzM1MDY4OGFkaXF6a2N4",
      "barcode": "X6LP3T7T",
      "type": "CS01",
      "date": "2017-12-20",
      "category": "confirmation-statement",
      "description": "confirmation-statement-with-no-updates",
      "description_values": {
        "made_up_date": "2017-10-24"
      },
      "pages": 3,
      "action_date": "2017-10-24",
      "links": {
        "self": "/company/10443894/filing-history/MzE5MzM1MDY4OGFkaXF6a2N4",
        "document_metadata": "https://document-api.company-information.service.gov.uk/document/toGh2UHoDmr2hKD7rv3F1Chxb6xWNKjGhtCOic6LMY8"
      }
    },
    {
      "transaction_id": "MzE2MDM0OTI3NWFkaXF6a2N4",
      "barcode": "X5IA1WYB",
      "type": "NEWINC",
      "date": "2016-10-25",
      "category": "incorporation",
      "associated_filings": [
        {
          "category": "capital",
          "date": "2016-10-25",
          "description": "statement-of-capital",
          "type": "SH01",
          "description_values": {
            "date": "2016-10-25",
            "capital": [
              {
                "currency": "GBP",
                "figure": "100"
              }
            ]
          },
          "action_date": "2016-10-25"
        },
        {
          "category": "incorporation",
          "date": "2016-10-25",
          "description": "model-articles-adopted",
          "type": "MODEL ARTICLES"
        }
      ],
      "description": "incorporation-company",
      "pages": 11,
      "links": {
        "self": "/company/10443894/filing-history/MzE2MDM0OTI3NWFkaXF6a2N4",
        "document_metadata": "https://document-api.company-information.service.gov.uk/document/Axmj0wl5__dj9Tfyatzvco4g3msaupZsShweNptloa4"
      }
    }
  ]
}
